examples/minimal_example.py
examples/population_plots.py
pan_biclustering/__init__.py
pan_biclustering/hypervolume.py
pan_biclustering/pan.py
pan_biclustering-1.0.0.dist-info/LICENSE
pan_biclustering-1.0.0.dist-info/METADATA
pan_biclustering-1.0.0.dist-info/WHEEL
pan_biclustering-1.0.0.dist-info/top_level.txt
pan_biclustering-1.0.0.dist-info/RECORD
