Metadata-Version: 2.1
Name: pan_biclustering
Version: 1.0.0
Summary: Python implementation of the PAN biclustering algorithm
Project-URL: Homepage, https://github.com/zwouter/PAN
Project-URL: Issues, https://github.com/zwouter/PAN/issues
Keywords: PAN,BICLUSTERING,PARETO-SET-ANALYSIS
Classifier: Programming Language :: Python :: 3
Classifier: License :: OSI Approved :: MIT License
Classifier: Operating System :: OS Independent
Requires-Python: >=3.8
License-File: LICENSE
Requires-Dist: numpy
Requires-Dist: tqdm
Requires-Dist: kmedoids
